pybrightness/__init__.py
pybrightness/controller.py
pybrightness/module.py
pybrightness-0.5.1.dist-info/LICENSE
pybrightness-0.5.1.dist-info/METADATA
pybrightness-0.5.1.dist-info/WHEEL
pybrightness-0.5.1.dist-info/top_level.txt
pybrightness-0.5.1.dist-info/RECORD
