Metadata-Version: 2.1
Name: pybrightness
Version: 0.5.1
Summary: Python module to modify screen brightness on Linux, Windows and macOS
Author-email: Vignesh Sivanandha Rao <svignesh1793@gmail.com>
License: MIT License
Project-URL: Homepage, https://github.com/thevickypedia/pybrightness
Project-URL: Source, https://github.com/thevickypedia/pybrightness
Project-URL: Bug Tracker, https://github.com/thevickypedia/pybrightness/issues
Project-URL: Release Notes, https://github.com/thevickypedia/pybrightness/blob/main/release_notes.rst
Keywords: pybrightness,display-settings,brightness-control
Classifier: Development Status :: 5 - Production/Stable
Classifier: Programming Language :: Python :: 3.9
Classifier: License :: OSI Approved :: MIT License
Classifier: Operating System :: MacOS :: MacOS X
Classifier: Operating System :: Microsoft :: Windows
Classifier: Operating System :: POSIX :: Linux
Classifier: Topic :: Terminals :: Terminal Emulators/X Terminals
Requires-Python: >=3
License-File: LICENSE
Requires-Dist: python-dotenv >=0.21.0 ; platform_system == "Linux"
Provides-Extra: dev
Requires-Dist: pre-commit ; extra == 'dev'
